llm_web.py
llm_web-0.8.dist-info/LICENSE
llm_web-0.8.dist-info/METADATA
llm_web-0.8.dist-info/WHEEL
llm_web-0.8.dist-info/entry_points.txt
llm_web-0.8.dist-info/top_level.txt
llm_web-0.8.dist-info/RECORD
