Metadata-Version: 2.1
Name: llm-web
Version: 0.8
Summary: plugin for simonw's llm to add a web search LLM agent
Author: thiswillbeyourgithub
License: GNU GENERAL PUBLIC LICENSE
Keywords: llm,openai,agent,simonw,websearch,web,search
Requires-Python: >=3.9
License-File: LICENSE
Requires-Dist: langchain ==0.0.336
Requires-Dist: numexpr ==2.8.7
Requires-Dist: duckduckgo-search ==3.9.5
Requires-Dist: wikipedia ==1.4.0
Requires-Dist: tqdm ==4.66.1
Requires-Dist: metaphor-python ==0.1.20
Requires-Dist: xmltodict ==0.13.0
Requires-Dist: arxiv ==2.0.0
